testrepo1/__init__.py
testrepo1/py.typed
testrepo1-0.0.0.dist-info/LICENSE
testrepo1-0.0.0.dist-info/METADATA
testrepo1-0.0.0.dist-info/WHEEL
testrepo1-0.0.0.dist-info/top_level.txt
testrepo1-0.0.0.dist-info/RECORD
