Metadata-Version: 2.1
Name: testrepo1
Version: 0.0.0
Summary: Python Projects Perfected: Innovate, Develop, and Deploy Effortlessl 
Author: Armin Ariamajd
Maintainer: Armin Ariamajd
License: GNU AFFERO GENERAL PUBLIC LICENSE
Project-URL: Homepage, https://aariam.github.io/testrepo1
Project-URL: Download, https://github.com/AAriam/testrepo1/releases
Project-URL: News, https://aariam.github.io/testrepo1/news
Project-URL: Documentation, https://aariam.github.io/testrepo1
Project-URL: Issue-Tracker, https://github.com/AAriam/testrepo1/issues
Project-URL: Sponsor, https://aariam.github.io/testrepo1/contribute/collaborate/maintain/sponsor
Project-URL: Source, https://github.com/AAriam/testrepo1
Keywords: python,github,packaging,template,dynamic repository,repository template,documentation,testing,deployment,maintenance,automation,development,infrastructure,streamline
Classifier: License :: OSI Approved :: GNU Affero General Public License v3 or later (AGPLv3+)
Classifier: Natural Language :: English
Classifier: Operating System :: MacOS
Classifier: Operating System :: Microsoft :: Windows
Classifier: Operating System :: POSIX :: Linux
Classifier: Programming Language :: Python :: 3 :: Only
Classifier: Programming Language :: Python :: 3.10
Classifier: Programming Language :: Python :: 3.11
Classifier: Programming Language :: Python :: 3.12
Classifier: Programming Language :: Python :: 3.9
Classifier: Typing :: Typed
Requires-Python: >=3.9
License-File: LICENSE
Requires-Dist: numpy >=1.21.2
